Constellation_OrderBoard-0.2.1.dist-info/DESCRIPTION.rst
Constellation_OrderBoard-0.2.1.dist-info/METADATA
Constellation_OrderBoard-0.2.1.dist-info/RECORD
Constellation_OrderBoard-0.2.1.dist-info/WHEEL
Constellation_OrderBoard-0.2.1.dist-info/metadata.json
Constellation_OrderBoard-0.2.1.dist-info/top_level.txt
constellation_orderboard/__init__.py
constellation_orderboard/admin.py
constellation_orderboard/apps.py
constellation_orderboard/forms.py
constellation_orderboard/models.py
constellation_orderboard/tests.py
constellation_orderboard/urls.py
constellation_orderboard/util.py
constellation_orderboard/views.py
constellation_orderboard/migrations/0001_initial.py
constellation_orderboard/migrations/0002_units.py
constellation_orderboard/migrations/0003_permissions.py
constellation_orderboard/migrations/__init__.py
constellation_orderboard/static/constellation_orderboard/css/orderboard.css
constellation_orderboard/static/constellation_orderboard/js/archive.js
constellation_orderboard/static/constellation_orderboard/js/edit-board.js
constellation_orderboard/static/constellation_orderboard/js/manage-boards.js
constellation_orderboard/static/constellation_orderboard/js/manage-stages.js
constellation_orderboard/static/constellation_orderboard/js/orderboard.js
constellation_orderboard/static/constellation_orderboard/js/view-list.js
constellation_orderboard/templates/constellation_orderboard/archive.html
constellation_orderboard/templates/constellation_orderboard/board.html
constellation_orderboard/templates/constellation_orderboard/dashboard.html
constellation_orderboard/templates/constellation_orderboard/edit-board.html
constellation_orderboard/templates/constellation_orderboard/manage-boards.html
constellation_orderboard/templates/constellation_orderboard/manage-stages.html
constellation_orderboard/templates/constellation_orderboard/view-list.html
