Metadata-Version: 2.0
Name: Constellation-OrderBoard
Version: 0.2.1
Summary: Constellation Suite - Order Management
Home-page: https://github.com/ConstellationApps/
Author: Constellation Developers
Author-email: bugs@constellationapps.org
License: ISC License
Platform: UNKNOWN
Classifier: Environment :: Web Environment
Classifier: Framework :: Django
Classifier: Intended Audience :: Developers
Classifier: License :: OSI Approved :: ISC License (ISCL)
Classifier: Operating System :: OS Independent
Classifier: Programming Language :: Python
Classifier: Topic :: Internet :: WWW/HTTP
Classifier: Topic :: Internet :: WWW/HTTP :: Dynamic Content
Classifier: Topic :: Office/Business :: Financial :: Accounting
Classifier: Development Status :: 4 - Beta
Requires-Dist: constellation-base (>=0.1.3)
Requires-Dist: django-guardian
